{
  "files": [
    {
      "path": "public/assets/application-*.js",
      "maxSize": "188 kB"
    },
    {
      "path": "public/assets/base-*.js",
      "maxSize": "73 kB"
    },
    {
      "path": "public/assets/hello-dev-*.js",
      "maxSize": "0.6 kB"
    },
    {
      "path": "public/assets/internal-*.js",
      "maxSize": "91 kB"
    },
    {
      "path": "public/assets/s3_direct_upload-*.js",
      "maxSize": "23 kB"
    },
    {
      "path": "public/packs/analyticsArticle-*.js",
      "maxSize": "1.7 kB"
    },
    {
      "path": "public/packs/analyticsDashboard-*.js",
      "maxSize": "1.8 kB"
    },
    {
      "path": "public/packs/articleForm-*.js",
      "maxSize": "10.5 kB"
    },
    {
      "path": "public/packs/Chat-*.js",
      "maxSize": "17 kB"
    },
    {
      "path": "public/packs/clipboardCopy-*.js",
      "maxSize": "0.5 kB"
    },
    {
      "path": "public/packs/colorPicker-*.js",
      "maxSize": "1.2 kB"
    },
    {
      "path": "public/packs/colorPreview-*.js",
      "maxSize": "0.5 kB"
    },
    {
      "path": "public/packs/contentDisplayPolicy-*.js",
      "maxSize": "1.1 kB"
    },
    {
      "path": "public/packs/githubRepos-*.js",
      "maxSize": "1.8 kB"
    },
    {
      "path": "public/packs/history-*.js",
      "maxSize": "3.2 kB"
    },
    {
      "path": "public/packs/homePage-*.js",
      "maxSize": "1 kB"
    },
    {
      "path": "public/packs/internal-*.js",
      "maxSize": "1.2 kB"
    },
    {
      "path": "public/packs/listingDashboard-*.js",
      "maxSize": "2.5 kB"
    },
    {
      "path": "public/packs/listingForm-*.js",
      "maxSize": "5.2 kB"
    },
    {
      "path": "public/packs/listings-*.js",
      "maxSize": "4.2 kB"
    },
    {
      "path": "public/packs/manifest-*.js",
      "maxSize": "1.1 kB"
    },
    {
      "path": "public/packs/notificationSubscriptionHandler-*.js",
      "maxSize": "0.9 kB"
    },
    {
      "path": "public/packs/Onboarding-*.js",
      "maxSize": "3 kB"
    },
    {
      "path": "public/packs/onboardingRedirectCheck-*.js",
      "maxSize": "3.2 kB"
    },
    {
      "path": "public/packs/orgCreditsSelector-*.js",
      "maxSize": "0.5 kB"
    },
    {
      "path": "public/packs/profileDropdown-*.js",
      "maxSize": "0.9 kB"
    },
    {
      "path": "public/packs/readingList-*.js",
      "maxSize": "4.1 kB"
    },
    {
      "path": "public/packs/Search-*.js",
      "maxSize": "2.1 kB"
    },
    {
      "path": "public/packs/sidebarWidget-*.js",
      "maxSize": "1.9 kB"
    },
    {
      "path": "public/packs/vendor-*.js",
      "maxSize": "34 kB"
    },
    {
      "path": "public/packs/webShare-*.js",
      "maxSize": "0.3 kB"
    }
  ]
}
